MANIFEST.in
README.txt
plonetheme.xtheme-configure.zcml
setup.py
docs/AUTHORS.txt
docs/HISTORY.txt
docs/INSTALL.txt
docs/LICENSE.GPL
docs/LICENSE.txt
plonetheme/__init__.py
plonetheme.xtheme.egg-info/PKG-INFO
plonetheme.xtheme.egg-info/SOURCES.txt
plonetheme.xtheme.egg-info/dependency_links.txt
plonetheme.xtheme.egg-info/entry_points.txt
plonetheme.xtheme.egg-info/namespace_packages.txt
plonetheme.xtheme.egg-info/not-zip-safe
plonetheme.xtheme.egg-info/requires.txt
plonetheme.xtheme.egg-info/top_level.txt
plonetheme/xtheme/__init__.py
plonetheme/xtheme/configure.zcml
plonetheme/xtheme/profiles.zcml
plonetheme/xtheme/setuphandlers.py
plonetheme/xtheme/skins.zcml
plonetheme/xtheme/version.txt
plonetheme/xtheme/Extensions/Install.py
plonetheme/xtheme/Extensions/__init__.py
plonetheme/xtheme/browser/__init__.py
plonetheme/xtheme/browser/configure.zcml
plonetheme/xtheme/browser/interfaces.py
plonetheme/xtheme/browser/viewlet.pt
plonetheme/xtheme/browser/viewlets.py
plonetheme/xtheme/browser/images/README.txt
plonetheme/xtheme/browser/images/columna_portlet.jpg
plonetheme/xtheme/browser/images/edc.jpg
plonetheme/xtheme/browser/images/eic.jpg
plonetheme/xtheme/browser/images/gnav_left.jpg
plonetheme/xtheme/browser/images/gnav_left_inv.jpg
plonetheme/xtheme/browser/images/gnav_right.jpg
plonetheme/xtheme/browser/images/gnav_right_inv.jpg
plonetheme/xtheme/browser/images/info_icon2.jpg
plonetheme/xtheme/browser/images/izq2.jpg
plonetheme/xtheme/browser/images/login2.jpg
plonetheme/xtheme/browser/images/portlet_left.jpg
plonetheme/xtheme/browser/images/portlet_right.jpg
plonetheme/xtheme/browser/images/search.jpg
plonetheme/xtheme/browser/scripts/main.js
plonetheme/xtheme/browser/stylesheets/README.txt
plonetheme/xtheme/browser/templates/path_bar.pt
plonetheme/xtheme/browser/templates/personal_bar.pt
plonetheme/xtheme/browser/templates/sections.pt
plonetheme/xtheme/browser/templates/site_actions.pt
plonetheme/xtheme/profiles/default/cssregistry.xml
plonetheme/xtheme/profiles/default/import_steps.xml
plonetheme/xtheme/profiles/default/jsregistry.xml
plonetheme/xtheme/profiles/default/metadata.xml
plonetheme/xtheme/profiles/default/plonetheme.xtheme_various.txt
plonetheme/xtheme/profiles/default/skins.xml
plonetheme/xtheme/profiles/default/viewlets.xml
plonetheme/xtheme/profiles/uninstall/cssregistry.xml
